MANIFEST.in
setup.py
awsutils/__init__.py
awsutils/s3/__init__.py
awsutils/s3/__main__.py
awsutils/s3/_version.py
awsutils/s3/commands.py
awsutils/s3/s3.py
awsutils/s3/url.py
awsutils_s3.egg-info/PKG-INFO
awsutils_s3.egg-info/SOURCES.txt
awsutils_s3.egg-info/dependency_links.txt
awsutils_s3.egg-info/entry_points.txt
awsutils_s3.egg-info/namespace_packages.txt
awsutils_s3.egg-info/requires.txt
awsutils_s3.egg-info/top_level.txt