Metadata-Version: 1.0
Name: awsutils-s3
Version: 0.3.19
Summary: AWS Command Line Interface wrapper for S3 services.
Home-page: https://github.com/mrstephenneal/awsutils-s3
Author: Stephen Neal
Author-email: stephen@stephenneal.net
License: MIT
Platform: UNKNOWN
